workhub_client/__init__.py
workhub_client/workhub.py
workhub_client-1.0.7.dist-info/METADATA
workhub_client-1.0.7.dist-info/WHEEL
workhub_client-1.0.7.dist-info/top_level.txt
workhub_client-1.0.7.dist-info/RECORD
