Metadata-Version: 2.1
Name: workhub_client
Version: 1.0.7
Summary: Python API to use WorkHub API for conversational AI.
Author: WorkHub Platform Inc.
Author-email: ashaheen@workhub.ai
Requires-Dist: requests
